neuralken/__init__.py
neuralken/neuralnetwork.py
neuralken-0.0.2.dist-info/METADATA
neuralken-0.0.2.dist-info/WHEEL
neuralken-0.0.2.dist-info/licenses/LICENCE.txt
neuralken-0.0.2.dist-info/RECORD
